{
    "FactionId": 0,
    "BuildingType": 14,
    "Quality": 7,
    "NameSeed": 0,
    "RmbSubRecord": {
        "XPos": 1920,
        "ZPos": 2048,
        "YRotation": 0,
        "Exterior": {
            "Header": {
                "Num3dObjectRecords": 1,
                "NumFlatObjectRecords": 0,
                "NumSection3Records": 0,
                "NumPeopleRecords": 0,
                "NumDoorRecords": 0
            },
            "Block3dObjectRecords": [
                {
                    "ModelId": "363",
                    "ModelIdNum": 363,
                    "ObjectType": 4,
                    "XPos": 0,
                    "YPos": 0,
                    "ZPos": 0,
                    "XRotation": 0,
                    "YRotation": 0,
                    "ZRotation": 0
                }
            ],
            "BlockFlatObjectRecords": [],
            "BlockSection3Records": [],
            "BlockPeopleRecords": [],
            "BlockDoorRecords": []
        },
        "Interior": {
            "Header": {
                "Num3dObjectRecords": 10,
                "NumFlatObjectRecords": 14,
                "NumSection3Records": 14,
                "NumPeopleRecords": 9,
                "NumDoorRecords": 2
            },
            "Block3dObjectRecords": [
                {
                    "ModelId": "41006",
                    "ModelIdNum": 41006,
                    "ObjectType": 3,
                    "XPos": -433,
                    "YPos": 0,
                    "ZPos": 329,
                    "XRotation": 0,
                    "YRotation": -1536,
                    "ZRotation": 0
                },
                {
                    "ModelId": "41006",
                    "ModelIdNum": 41006,
                    "ObjectType": 3,
                    "XPos": 261,
                    "YPos": 0,
                    "ZPos": 203,
                    "XRotation": 0,
                    "YRotation": -1024,
                    "ZRotation": 0
                },
                {
                    "ModelId": "31623",
                    "ModelIdNum": 31623,
                    "ObjectType": 0,
                    "XPos": 0,
                    "YPos": 259,
                    "ZPos": -132,
                    "XRotation": 0,
                    "YRotation": -512,
                    "ZRotation": 0
                },
                {
                    "ModelId": "31623",
                    "ModelIdNum": 31623,
                    "ObjectType": 0,
                    "XPos": -256,
                    "YPos": 259,
                    "ZPos": -132,
                    "XRotation": 0,
                    "YRotation": -1536,
                    "ZRotation": 0
                },
                {
                    "ModelId": "31605",
                    "ModelIdNum": 31605,
                    "ObjectType": 0,
                    "XPos": -128,
                    "YPos": 67,
                    "ZPos": 124,
                    "XRotation": 0,
                    "YRotation": -1024,
                    "ZRotation": 0
                },
                {
                    "ModelId": "31625",
                    "ModelIdNum": 31625,
                    "ObjectType": 0,
                    "XPos": -128,
                    "YPos": 67,
                    "ZPos": -4,
                    "XRotation": 0,
                    "YRotation": 0,
                    "ZRotation": 0
                },
                {
                    "ModelId": "31605",
                    "ModelIdNum": 31605,
                    "ObjectType": 0,
                    "XPos": -256,
                    "YPos": 67,
                    "ZPos": -4,
                    "XRotation": 0,
                    "YRotation": -512,
                    "ZRotation": 0
                },
                {
                    "ModelId": "32600",
                    "ModelIdNum": 32600,
                    "ObjectType": 13,
                    "XPos": -256,
                    "YPos": 67,
                    "ZPos": 313,
                    "XRotation": 0,
                    "YRotation": 0,
                    "ZRotation": 0
                },
                {
                    "ModelId": "31627",
                    "ModelIdNum": 31627,
                    "ObjectType": 0,
                    "XPos": -384,
                    "YPos": 130,
                    "ZPos": -4,
                    "XRotation": 0,
                    "YRotation": -1536,
                    "ZRotation": 0
                },
                {
                    "ModelId": "31606",
                    "ModelIdNum": 31606,
                    "ObjectType": 0,
                    "XPos": -387,
                    "YPos": 67,
                    "ZPos": 121,
                    "XRotation": 0,
                    "YRotation": -1536,
                    "ZRotation": 0
                },
                {
                    "ModelId": "31606",
                    "ModelIdNum": 31606,
                    "ObjectType": 0,
                    "XPos": -509,
                    "YPos": 67,
                    "ZPos": 121,
                    "XRotation": 0,
                    "YRotation": -1024,
                    "ZRotation": 0
                },
                {
                    "ModelId": "31606",
                    "ModelIdNum": 31606,
                    "ObjectType": 0,
                    "XPos": -509,
                    "YPos": 67,
                    "ZPos": -1,
                    "XRotation": 0,
                    "YRotation": -512,
                    "ZRotation": 0
                },
                {
                    "ModelId": "31606",
                    "ModelIdNum": 31606,
                    "ObjectType": 0,
                    "XPos": 125,
                    "YPos": 67,
                    "ZPos": 127,
                    "XRotation": 0,
                    "YRotation": 0,
                    "ZRotation": 0
                },
                {
                    "ModelId": "31624",
                    "ModelIdNum": 31624,
                    "ObjectType": 0,
                    "XPos": 0,
                    "YPos": 130,
                    "ZPos": 252,
                    "XRotation": 0,
                    "YRotation": -1024,
                    "ZRotation": 0
                },
                {
                    "ModelId": "31624",
                    "ModelIdNum": 31624,
                    "ObjectType": 0,
                    "XPos": 0,
                    "YPos": 130,
                    "ZPos": 380,
                    "XRotation": 0,
                    "YRotation": -1024,
                    "ZRotation": 0
                },
                {
                    "ModelId": "31624",
                    "ModelIdNum": 31624,
                    "ObjectType": 0,
                    "XPos": 128,
                    "YPos": 130,
                    "ZPos": 380,
                    "XRotation": 0,
                    "YRotation": 0,
                    "ZRotation": 0
                },
                {
                    "ModelId": "31606",
                    "ModelIdNum": 31606,
                    "ObjectType": 0,
                    "XPos": 125,
                    "YPos": 67,
                    "ZPos": 505,
                    "XRotation": 0,
                    "YRotation": -1536,
                    "ZRotation": 0
                },
                {
                    "ModelId": "31606",
                    "ModelIdNum": 31606,
                    "ObjectType": 0,
                    "XPos": 3,
                    "YPos": 67,
                    "ZPos": 505,
                    "XRotation": 0,
                    "YRotation": -1024,
                    "ZRotation": 0
                },
                {
                    "ModelId": "31606",
                    "ModelIdNum": 31606,
                    "ObjectType": 0,
                    "XPos": -381,
                    "YPos": 194,
                    "ZPos": -129,
                    "XRotation": 0,
                    "YRotation": -512,
                    "ZRotation": 0
                },
                {
                    "ModelId": "31606",
                    "ModelIdNum": 31606,
                    "ObjectType": 0,
                    "XPos": -381,
                    "YPos": 194,
                    "ZPos": -7,
                    "XRotation": 0,
                    "YRotation": -1024,
                    "ZRotation": 0
                },
                {
                    "ModelId": "31600",
                    "ModelIdNum": 31600,
                    "ObjectType": 0,
                    "XPos": -256,
                    "YPos": 194,
                    "ZPos": -4,
                    "XRotation": 0,
                    "YRotation": -512,
                    "ZRotation": 0
                },
                {
                    "ModelId": "31606",
                    "ModelIdNum": 31606,
                    "ObjectType": 0,
                    "XPos": 125,
                    "YPos": 194,
                    "ZPos": -129,
                    "XRotation": 0,
                    "YRotation": 0,
                    "ZRotation": 0
                },
                {
                    "ModelId": "31600",
                    "ModelIdNum": 31600,
                    "ObjectType": 0,
                    "XPos": 0,
                    "YPos": 194,
                    "ZPos": -4,
                    "XRotation": 0,
                    "YRotation": -512,
                    "ZRotation": 0
                },
                {
                    "ModelId": "31605",
                    "ModelIdNum": 31605,
                    "ObjectType": 0,
                    "XPos": -128,
                    "YPos": 194,
                    "ZPos": 124,
                    "XRotation": 0,
                    "YRotation": -1024,
                    "ZRotation": 0
                },
                {
                    "ModelId": "63033",
                    "ModelIdNum": 63033,
                    "ObjectType": 0,
                    "XPos": 192,
                    "YPos": 257,
                    "ZPos": 636,
                    "XRotation": 0,
                    "YRotation": 0,
                    "ZRotation": 0
                },
                {
                    "ModelId": "63033",
                    "ModelIdNum": 63033,
                    "ObjectType": 0,
                    "XPos": -320,
                    "YPos": 257,
                    "ZPos": 508,
                    "XRotation": 0,
                    "YRotation": -512,
                    "ZRotation": 0
                },
                {
                    "ModelId": "63033",
                    "ModelIdNum": 63033,
                    "ObjectType": 0,
                    "XPos": 64,
                    "YPos": 257,
                    "ZPos": 1404,
                    "XRotation": 0,
                    "YRotation": -1536,
                    "ZRotation": 0
                },
                {
                    "ModelId": "63033",
                    "ModelIdNum": 63033,
                    "ObjectType": 0,
                    "XPos": -832,
                    "YPos": 257,
                    "ZPos": 252,
                    "XRotation": 0,
                    "YRotation": -512,
                    "ZRotation": 0
                },
                {
                    "ModelId": "63033",
                    "ModelIdNum": 63033,
                    "ObjectType": 0,
                    "XPos": -192,
                    "YPos": 257,
                    "ZPos": 1916,
                    "XRotation": 0,
                    "YRotation": -1536,
                    "ZRotation": 0
                },
                {
                    "ModelId": "63033",
                    "ModelIdNum": 63033,
                    "ObjectType": 0,
                    "XPos": -64,
                    "YPos": 257,
                    "ZPos": 1660,
                    "XRotation": 0,
                    "YRotation": 0,
                    "ZRotation": 0
                },
                {
                    "ModelId": "63033",
                    "ModelIdNum": 63033,
                    "ObjectType": 0,
                    "XPos": -704,
                    "YPos": 257,
                    "ZPos": 1788,
                    "XRotation": 0,
                    "YRotation": -1024,
                    "ZRotation": 0
                },
                {
                    "ModelId": "63033",
                    "ModelIdNum": 63033,
                    "ObjectType": 0,
                    "XPos": -1216,
                    "YPos": 257,
                    "ZPos": 1788,
                    "XRotation": 0,
                    "YRotation": -1024,
                    "ZRotation": 0
                },
                {
                    "ModelId": "63033",
                    "ModelIdNum": 63033,
                    "ObjectType": 0,
                    "XPos": -960,
                    "YPos": 257,
                    "ZPos": 1916,
                    "XRotation": 0,
                    "YRotation": -1536,
                    "ZRotation": 0
                },
                {
                    "ModelId": "63033",
                    "ModelIdNum": 63033,
                    "ObjectType": 0,
                    "XPos": -1088,
                    "YPos": 257,
                    "ZPos": 1532,
                    "XRotation": 0,
                    "YRotation": -512,
                    "ZRotation": 0
                },
                {
                    "ModelId": "63033",
                    "ModelIdNum": 63033,
                    "ObjectType": 0,
                    "XPos": 704,
                    "YPos": 257,
                    "ZPos": 380,
                    "XRotation": 0,
                    "YRotation": 0,
                    "ZRotation": 0
                },
                {
                    "ModelId": "63033",
                    "ModelIdNum": 63033,
                    "ObjectType": 0,
                    "XPos": 192,
                    "YPos": 257,
                    "ZPos": 1532,
                    "XRotation": 0,
                    "YRotation": -512,
                    "ZRotation": 0
                },
                {
                    "ModelId": "63042",
                    "ModelIdNum": 63042,
                    "ObjectType": 0,
                    "XPos": -64,
                    "YPos": 257,
                    "ZPos": 892,
                    "XRotation": 0,
                    "YRotation": 0,
                    "ZRotation": 0
                },
                {
                    "ModelId": "63042",
                    "ModelIdNum": 63042,
                    "ObjectType": 0,
                    "XPos": -64,
                    "YPos": 257,
                    "ZPos": 1148,
                    "XRotation": 0,
                    "YRotation": 0,
                    "ZRotation": 0
                },
                {
                    "ModelId": "63028",
                    "ModelIdNum": 63028,
                    "ObjectType": 0,
                    "XPos": -192,
                    "YPos": 257,
                    "ZPos": 1276,
                    "XRotation": 0,
                    "YRotation": -1024,
                    "ZRotation": 0
                },
                {
                    "ModelId": "63028",
                    "ModelIdNum": 63028,
                    "ObjectType": 0,
                    "XPos": -320,
                    "YPos": 257,
                    "ZPos": 764,
                    "XRotation": 0,
                    "YRotation": -512,
                    "ZRotation": 0
                },
                {
                    "ModelId": "63028",
                    "ModelIdNum": 63028,
                    "ObjectType": 0,
                    "XPos": -320,
                    "YPos": 257,
                    "ZPos": 1020,
                    "XRotation": 0,
                    "YRotation": -512,
                    "ZRotation": 0
                },
                {
                    "ModelId": "63028",
                    "ModelIdNum": 63028,
                    "ObjectType": 0,
                    "XPos": 64,
                    "YPos": 257,
                    "ZPos": 892,
                    "XRotation": 0,
                    "YRotation": -1536,
                    "ZRotation": 0
                },
                {
                    "ModelId": "63028",
                    "ModelIdNum": 63028,
                    "ObjectType": 0,
                    "XPos": 64,
                    "YPos": 257,
                    "ZPos": 1148,
                    "XRotation": 0,
                    "YRotation": -1536,
                    "ZRotation": 0
                },
                {
                    "ModelId": "63028",
                    "ModelIdNum": 63028,
                    "ObjectType": 0,
                    "XPos": -704,
                    "YPos": 257,
                    "ZPos": 892,
                    "XRotation": 0,
                    "YRotation": -1536,
                    "ZRotation": 0
                },
                {
                    "ModelId": "63028",
                    "ModelIdNum": 63028,
                    "ObjectType": 0,
                    "XPos": -704,
                    "YPos": 257,
                    "ZPos": 1148,
                    "XRotation": 0,
                    "YRotation": -1536,
                    "ZRotation": 0
                },
                {
                    "ModelId": "63028",
                    "ModelIdNum": 63028,
                    "ObjectType": 0,
                    "XPos": -704,
                    "YPos": 257,
                    "ZPos": 636,
                    "XRotation": 0,
                    "YRotation": -1536,
                    "ZRotation": 0
                },
                {
                    "ModelId": "63028",
                    "ModelIdNum": 63028,
                    "ObjectType": 0,
                    "XPos": -832,
                    "YPos": 257,
                    "ZPos": 764,
                    "XRotation": 0,
                    "YRotation": -512,
                    "ZRotation": 0
                },
                {
                    "ModelId": "63028",
                    "ModelIdNum": 63028,
                    "ObjectType": 0,
                    "XPos": -832,
                    "YPos": 257,
                    "ZPos": 1020,
                    "XRotation": 0,
                    "YRotation": -512,
                    "ZRotation": 0
                },
                {
                    "ModelId": "63028",
                    "ModelIdNum": 63028,
                    "ObjectType": 0,
                    "XPos": -832,
                    "YPos": 257,
                    "ZPos": 508,
                    "XRotation": 0,
                    "YRotation": -512,
                    "ZRotation": 0
                },
                {
                    "ModelId": "63028",
                    "ModelIdNum": 63028,
                    "ObjectType": 0,
                    "XPos": -576,
                    "YPos": 257,
                    "ZPos": 380,
                    "XRotation": 0,
                    "YRotation": 0,
                    "ZRotation": 0
                },
                {
                    "ModelId": "63028",
                    "ModelIdNum": 63028,
                    "ObjectType": 0,
                    "XPos": -448,
                    "YPos": 257,
                    "ZPos": 1788,
                    "XRotation": 0,
                    "YRotation": -1024,
                    "ZRotation": 0
                },
                {
                    "ModelId": "63028",
                    "ModelIdNum": 63028,
                    "ObjectType": 0,
                    "XPos": 448,
                    "YPos": 257,
                    "ZPos": 764,
                    "XRotation": 0,
                    "YRotation": -512,
                    "ZRotation": 0
                },
                {
                    "ModelId": "63028",
                    "ModelIdNum": 63028,
                    "ObjectType": 0,
                    "XPos": 448,
                    "YPos": 257,
                    "ZPos": 1020,
                    "XRotation": 0,
                    "YRotation": -512,
                    "ZRotation": 0
                },
                {
                    "ModelId": "63028",
                    "ModelIdNum": 63028,
                    "ObjectType": 0,
                    "XPos": 448,
                    "YPos": 257,
                    "ZPos": 508,
                    "XRotation": 0,
                    "YRotation": -512,
                    "ZRotation": 0
                },
                {
                    "ModelId": "63028",
                    "ModelIdNum": 63028,
                    "ObjectType": 0,
                    "XPos": 448,
                    "YPos": 257,
                    "ZPos": 380,
                    "XRotation": 0,
                    "YRotation": 0,
                    "ZRotation": 0
                },
                {
                    "ModelId": "63052",
                    "ModelIdNum": 63052,
                    "ObjectType": 0,
                    "XPos": -384,
                    "YPos": 257,
                    "ZPos": 1340,
                    "XRotation": 0,
                    "YRotation": -1536,
                    "ZRotation": 0
                },
                {
                    "ModelId": "63000",
                    "ModelIdNum": 63000,
                    "ObjectType": 0,
                    "XPos": 192,
                    "YPos": 257,
                    "ZPos": 252,
                    "XRotation": 0,
                    "YRotation": -512,
                    "ZRotation": 0
                },
                {
                    "ModelId": "63000",
                    "ModelIdNum": 63000,
                    "ObjectType": 0,
                    "XPos": -320,
                    "YPos": 257,
                    "ZPos": 252,
                    "XRotation": 0,
                    "YRotation": -512,
                    "ZRotation": 0
                },
                {
                    "ModelId": "63007",
                    "ModelIdNum": 63007,
                    "ObjectType": 0,
                    "XPos": -960,
                    "YPos": 257,
                    "ZPos": 1276,
                    "XRotation": 0,
                    "YRotation": -1024,
                    "ZRotation": 0
                },
                {
                    "ModelId": "63007",
                    "ModelIdNum": 63007,
                    "ObjectType": 0,
                    "XPos": -704,
                    "YPos": 257,
                    "ZPos": 1276,
                    "XRotation": 0,
                    "YRotation": -1024,
                    "ZRotation": 0
                },
                {
                    "ModelId": "63007",
                    "ModelIdNum": 63007,
                    "ObjectType": 0,
                    "XPos": 320,
                    "YPos": 257,
                    "ZPos": 1276,
                    "XRotation": 0,
                    "YRotation": -1024,
                    "ZRotation": 0
                },
                {
                    "ModelId": "63051",
                    "ModelIdNum": 63051,
                    "ObjectType": 0,
                    "XPos": -640,
                    "YPos": 257,
                    "ZPos": 1596,
                    "XRotation": 0,
                    "YRotation": -1536,
                    "ZRotation": 0
                },
                {
                    "ModelId": "63029",
                    "ModelIdNum": 63029,
                    "ObjectType": 0,
                    "XPos": -320,
                    "YPos": 257,
                    "ZPos": 1660,
                    "XRotation": 0,
                    "YRotation": 0,
                    "ZRotation": 0
                },
                {
                    "ModelId": "63052",
                    "ModelIdNum": 63052,
                    "ObjectType": 0,
                    "XPos": -896,
                    "YPos": 257,
                    "ZPos": 1596,
                    "XRotation": 0,
                    "YRotation": -512,
                    "ZRotation": 0
                },
                {
                    "ModelId": "63052",
                    "ModelIdNum": 63052,
                    "ObjectType": 0,
                    "XPos": 384,
                    "YPos": 257,
                    "ZPos": 1596,
                    "XRotation": 0,
                    "YRotation": -512,
                    "ZRotation": 0
                },
                {
                    "ModelId": "74072",
                    "ModelIdNum": 74072,
                    "ObjectType": 0,
                    "XPos": -385,
                    "YPos": 225,
                    "ZPos": 1863,
                    "XRotation": 0,
                    "YRotation": -512,
                    "ZRotation": 0
                },
                {
                    "ModelId": "74073",
                    "ModelIdNum": 74073,
                    "ObjectType": 0,
                    "XPos": -383,
                    "YPos": 183,
                    "ZPos": 1832,
                    "XRotation": 0,
                    "YRotation": -512,
                    "ZRotation": 0
                },
                {
                    "ModelId": "41319",
                    "ModelIdNum": 41319,
                    "ObjectType": 0,
                    "XPos": -729,
                    "YPos": 215,
                    "ZPos": 567,
                    "XRotation": 0,
                    "YRotation": 0,
                    "ZRotation": 0
                },
                {
                    "ModelId": "62322",
                    "ModelIdNum": 62322,
                    "ObjectType": 0,
                    "XPos": -769,
                    "YPos": 244,
                    "ZPos": 572,
                    "XScale": 0.8,
                    "YScale": 0.8,
                    "ZScale": 0.8,
                    "XRotation": 0,
                    "YRotation": 0,
                    "ZRotation": 0
                },
                {
                    "ModelId": "41319",
                    "ModelIdNum": 41319,
                    "ObjectType": 0,
                    "XPos": -800,
                    "YPos": 215,
                    "ZPos": 567,
                    "XRotation": 0,
                    "YRotation": -1024,
                    "ZRotation": 0
                },
                {
                    "ModelId": "41319",
                    "ModelIdNum": 41319,
                    "ObjectType": 0,
                    "XPos": -729,
                    "YPos": 215,
                    "ZPos": 821,
                    "XRotation": 0,
                    "YRotation": 0,
                    "ZRotation": 0
                },
                {
                    "ModelId": "62322",
                    "ModelIdNum": 62322,
                    "ObjectType": 0,
                    "XPos": -769,
                    "YPos": 244,
                    "ZPos": 826,
                    "XScale": 0.8,
                    "YScale": 0.8,
                    "ZScale": 0.8,
                    "XRotation": 0,
                    "YRotation": 0,
                    "ZRotation": 0
                },
                {
                    "ModelId": "41319",
                    "ModelIdNum": 41319,
                    "ObjectType": 0,
                    "XPos": -800,
                    "YPos": 215,
                    "ZPos": 821,
                    "XRotation": 0,
                    "YRotation": -1024,
                    "ZRotation": 0
                },
                {
                    "ModelId": "41319",
                    "ModelIdNum": 41319,
                    "ObjectType": 0,
                    "XPos": -729,
                    "YPos": 215,
                    "ZPos": 1078,
                    "XRotation": 0,
                    "YRotation": 0,
                    "ZRotation": 0
                },
                {
                    "ModelId": "62322",
                    "ModelIdNum": 62322,
                    "ObjectType": 0,
                    "XPos": -769,
                    "YPos": 244,
                    "ZPos": 1083,
                    "XScale": 0.8,
                    "YScale": 0.8,
                    "ZScale": 0.8,
                    "XRotation": 0,
                    "YRotation": 0,
                    "ZRotation": 0
                },
                {
                    "ModelId": "41319",
                    "ModelIdNum": 41319,
                    "ObjectType": 0,
                    "XPos": -800,
                    "YPos": 215,
                    "ZPos": 1078,
                    "XRotation": 0,
                    "YRotation": -1024,
                    "ZRotation": 0
                },
                {
                    "ModelId": "51110",
                    "ModelIdNum": 51110,
                    "ObjectType": 0,
                    "XPos": -590,
                    "YPos": 232,
                    "ZPos": 442,
                    "XRotation": 0,
                    "YRotation": -512,
                    "ZRotation": 0
                },
                {
                    "ModelId": "51110",
                    "ModelIdNum": 51110,
                    "ObjectType": 0,
                    "XPos": -590,
                    "YPos": 232,
                    "ZPos": 702,
                    "XRotation": 0,
                    "YRotation": -512,
                    "ZRotation": 0
                },
                {
                    "ModelId": "51110",
                    "ModelIdNum": 51110,
                    "ObjectType": 0,
                    "XPos": -590,
                    "YPos": 232,
                    "ZPos": 956,
                    "XRotation": 0,
                    "YRotation": -512,
                    "ZRotation": 0
                },
                {
                    "ModelId": "51110",
                    "ModelIdNum": 51110,
                    "ObjectType": 0,
                    "XPos": -946,
                    "YPos": 232,
                    "ZPos": 442,
                    "XRotation": 0,
                    "YRotation": -512,
                    "ZRotation": 0
                },
                {
                    "ModelId": "51110",
                    "ModelIdNum": 51110,
                    "ObjectType": 0,
                    "XPos": -946,
                    "YPos": 232,
                    "ZPos": 702,
                    "XRotation": 0,
                    "YRotation": -512,
                    "ZRotation": 0
                },
                {
                    "ModelId": "51110",
                    "ModelIdNum": 51110,
                    "ObjectType": 0,
                    "XPos": -946,
                    "YPos": 232,
                    "ZPos": 956,
                    "XRotation": 0,
                    "YRotation": -512,
                    "ZRotation": 0
                }
            ]
        }
    },
    "AutoMapData": null
}